{
    "incidents": {
        "9578842": [
            {
                "playerIn": 965022,
                "playerOut": 94226,
                "time": 90,
                "incidentType": "substitution"
            },
            {
                "goalscorer": 188335,
                "assist": "N/A",
                "time": 90,
                "incidentType": "goal"
            },
            {
                "playerIn": 826915,
                "playerOut": 1090010,
                "time": 89,
                "incidentType": "substitution"
            },
            {
                "playerIn": 357590,
                "playerOut": 991390,
                "time": 87,
                "incidentType": "substitution"
            },
            {
                "playerIn": 826020,
                "playerOut": 932608,
                "time": 86,
                "incidentType": "substitution"
            },
            {
                "playerIn": 366848,
                "playerOut": 284843,
                "time": 84,
                "incidentType": "substitution"
            },
            {
                "playerIn": 948139,
                "playerOut": 857492,
                "time": 78,
                "incidentType": "substitution"
            },
            {
                "player": 808495,
                "card": "yellow",
                "time": 68,
                "incidentType": "card"
            },
            {
                "playerIn": 827367,
                "playerOut": 965019,
                "time": 46,
                "incidentType": "substitution"
            },
            {
                "playerIn": 137635,
                "playerOut": 883475,
                "time": 46,
                "incidentType": "substitution"
            }
        ],
        "9578840": [
            {
                "playerIn": 902370,
                "playerOut": 799037,
                "time": 88,
                "incidentType": "substitution"
            },
            {
                "playerIn": 98217,
                "playerOut": 94226,
                "time": 88,
                "incidentType": "substitution"
            },
            {
                "playerIn": 932608,
                "playerOut": 826020,
                "time": 87,
                "incidentType": "substitution"
            },
            {
                "playerIn": 330035,
                "playerOut": 841985,
                "time": 82,
                "incidentType": "substitution"
            },
            {
                "playerIn": 539260,
                "playerOut": 827367,
                "time": 82,
                "incidentType": "substitution"
            },
            {
                "player": 855908,
                "card": "yellow",
                "time": 81,
                "incidentType": "card"
            },
            {
                "playerIn": 1048919,
                "playerOut": 1120914,
                "time": 80,
                "incidentType": "substitution"
            },
            {
                "playerIn": 916181,
                "playerOut": 965019,
                "time": 73,
                "incidentType": "substitution"
            },
            {
                "playerIn": 70423,
                "playerOut": 285991,
                "time": 63,
                "incidentType": "substitution"
            },
            {
                "playerIn": 935054,
                "playerOut": 283851,
                "time": 63,
                "incidentType": "substitution"
            },
            {
                "player": 841985,
                "card": "yellow",
                "time": 54,
                "incidentType": "card"
            },
            {
                "player": 852471,
                "card": "yellow",
                "time": 51,
                "incidentType": "card"
            },
            {
                "goalscorer": 94226,
                "assist": 322417,
                "time": 48,
                "incidentType": "goal"
            },
            {
                "playerIn": 792156,
                "playerOut": 845373,
                "time": 46,
                "incidentType": "substitution"
            },
            {
                "goalscorer": 841985,
                "assist": 75417,
                "time": 35,
                "incidentType": "goal"
            },
            {
                "player": 283851,
                "card": "yellow",
                "time": 5,
                "incidentType": "card"
            }
        ],
        "9578831": [
            {
                "playerIn": 539260,
                "playerOut": 94226,
                "time": 90,
                "incidentType": "substitution"
            },
            {
                "playerIn": 826915,
                "playerOut": 932608,
                "time": 90,
                "incidentType": "substitution"
            },
            {
                "playerIn": 882588,
                "playerOut": 839388,
                "time": 88,
                "incidentType": "substitution"
            },
            {
                "playerIn": 872262,
                "playerOut": 359044,
                "time": 88,
                "incidentType": "substitution"
            },
            {
                "playerIn": 1126674,
                "playerOut": 826023,
                "time": 88,
                "incidentType": "substitution"
            },
            {
                "player": 359044,
                "card": "yellow",
                "time": 87,
                "incidentType": "card"
            },
            {
                "goalscorer": 94226,
                "assist": 827367,
                "time": 87,
                "incidentType": "goal"
            },
            {
                "player": 880745,
                "card": "yellow",
                "time": 81,
                "incidentType": "card"
            },
            {
                "player": 359624,
                "card": "yellow",
                "time": 79,
                "incidentType": "card"
            },
            {
                "playerIn": 283841,
                "playerOut": 880751,
                "time": 70,
                "incidentType": "substitution"
            },
            {
                "playerIn": 916181,
                "playerOut": 841985,
                "time": 67,
                "incidentType": "substitution"
            },
            {
                "playerIn": 127844,
                "playerOut": 916183,
                "time": 60,
                "incidentType": "substitution"
            },
            {
                "playerIn": 826020,
                "playerOut": 965019,
                "time": 59,
                "incidentType": "substitution"
            },
            {
                "goalscorer": 359044,
                "assist": 839388,
                "time": 56,
                "incidentType": "goal"
            },
            {
                "player": 137635,
                "card": "yellow",
                "time": 51,
                "incidentType": "card"
            },
            {
                "goalscorer": 137635,
                "assist": "N/A",
                "time": 45,
                "incidentType": "goal"
            },
            {
                "player": 916183,
                "card": "yellow",
                "time": 35,
                "incidentType": "card"
            },
            {
                "goalscorer": 827367,
                "assist": 94226,
                "time": 31,
                "incidentType": "goal"
            }
        ],
        "9653831": [
            {
                "player": 188335,
                "card": "yellow",
                "time": 90,
                "incidentType": "card"
            },
            {
                "player": 822505,
                "card": "yellow",
                "time": 90,
                "incidentType": "card"
            },
            {
                "playerIn": 880748,
                "playerOut": 322417,
                "time": 89,
                "incidentType": "substitution"
            },
            {
                "player": 841985,
                "card": "yellow",
                "time": 83,
                "incidentType": "card"
            },
            {
                "player": 57989,
                "card": "yellow",
                "time": 77,
                "incidentType": "card"
            },
            {
                "player": 932608,
                "card": "yellow",
                "time": 75,
                "incidentType": "card"
            },
            {
                "playerIn": 826020,
                "playerOut": 75417,
                "time": 74,
                "incidentType": "substitution"
            },
            {
                "playerIn": 916181,
                "playerOut": 965019,
                "time": 74,
                "incidentType": "substitution"
            },
            {
                "playerIn": 1131930,
                "playerOut": 70298,
                "time": 71,
                "incidentType": "substitution"
            },
            {
                "playerIn": 879722,
                "playerOut": 855970,
                "time": 71,
                "incidentType": "substitution"
            },
            {
                "playerIn": 1090010,
                "playerOut": 827367,
                "time": 62,
                "incidentType": "substitution"
            },
            {
                "player": 879392,
                "card": "yellow",
                "time": 57,
                "incidentType": "card"
            },
            {
                "playerIn": 822505,
                "playerOut": 797920,
                "time": 54,
                "incidentType": "substitution"
            },
            {
                "playerIn": 1048837,
                "playerOut": 897600,
                "time": 54,
                "incidentType": "substitution"
            },
            {
                "player": 848540,
                "card": "yellow",
                "time": 53,
                "incidentType": "card"
            },
            {
                "playerIn": 841985,
                "playerOut": 330035,
                "time": 46,
                "incidentType": "substitution"
            },
            {
                "goalscorer": 330035,
                "assist": 75417,
                "time": 26,
                "incidentType": "goal"
            },
            {
                "player": 897600,
                "card": "yellow",
                "time": 21,
                "incidentType": "card"
            },
            {
                "playerIn": 70298,
                "playerOut": 916186,
                "time": 16,
                "incidentType": "substitution"
            }
        ],
        "9578822": [
            {
                "player": 883475,
                "card": "yellow",
                "time": 90,
                "incidentType": "card"
            },
            {
                "playerIn": 826915,
                "playerOut": 880748,
                "time": 89,
                "incidentType": "substitution"
            },
            {
                "goalscorer": 921764,
                "assist": "N/A",
                "time": 87,
                "incidentType": "goal"
            },
            {
                "playerIn": 551406,
                "playerOut": 836200,
                "time": 85,
                "incidentType": "substitution"
            },
            {
                "playerIn": 883475,
                "playerOut": 827367,
                "time": 79,
                "incidentType": "substitution"
            },
            {
                "playerIn": 98217,
                "playerOut": 841985,
                "time": 71,
                "incidentType": "substitution"
            },
            {
                "playerIn": 970518,
                "playerOut": 75417,
                "time": 71,
                "incidentType": "substitution"
            },
            {
                "playerIn": 797775,
                "playerOut": 897603,
                "time": 71,
                "incidentType": "substitution"
            },
            {
                "playerIn": 921764,
                "playerOut": 75509,
                "time": 70,
                "incidentType": "substitution"
            },
            {
                "playerIn": 358598,
                "playerOut": 152402,
                "time": 70,
                "incidentType": "substitution"
            },
            {
                "goalscorer": 555538,
                "assist": "N/A",
                "time": 66,
                "incidentType": "goal"
            },
            {
                "goalscorer": 94226,
                "assist": "N/A",
                "time": 63,
                "incidentType": "goal"
            },
            {
                "player": 137635,
                "card": "yellow",
                "time": 55,
                "incidentType": "card"
            },
            {
                "playerIn": 51223,
                "playerOut": 839916,
                "time": 46,
                "incidentType": "substitution"
            },
            {
                "playerIn": 539260,
                "playerOut": 1090010,
                "time": 46,
                "incidentType": "substitution"
            },
            {
                "player": 880748,
                "card": "yellow",
                "time": 39,
                "incidentType": "card"
            },
            {
                "player": 94226,
                "card": "yellow",
                "time": 25,
                "incidentType": "card"
            },
            {
                "player": 322417,
                "card": "yellow",
                "time": 23,
                "incidentType": "card"
            },
            {
                "player": 70172,
                "card": "yellow",
                "time": 11,
                "incidentType": "card"
            }
        ],
        "9578844": [
            {
                "goalscorer": 933787,
                "assist": 995773,
                "time": 90,
                "incidentType": "goal"
            },
            {
                "playerIn": 933787,
                "playerOut": 886227,
                "time": 90,
                "incidentType": "substitution"
            },
            {
                "playerIn": 921764,
                "playerOut": 839916,
                "time": 86,
                "incidentType": "substitution"
            },
            {
                "goalscorer": 886227,
                "assist": 1009623,
                "time": 83,
                "incidentType": "goal"
            },
            {
                "playerIn": 990141,
                "playerOut": 839917,
                "time": 80,
                "incidentType": "substitution"
            },
            {
                "playerIn": 551406,
                "playerOut": 75509,
                "time": 68,
                "incidentType": "substitution"
            },
            {
                "playerIn": 152402,
                "playerOut": 51223,
                "time": 67,
                "incidentType": "substitution"
            },
            {
                "playerIn": 797775,
                "playerOut": 134877,
                "time": 67,
                "incidentType": "substitution"
            },
            {
                "player": 897603,
                "card": "yellow",
                "time": 61,
                "incidentType": "card"
            },
            {
                "playerIn": 108031,
                "playerOut": 117653,
                "time": 61,
                "incidentType": "substitution"
            },
            {
                "playerIn": 1034543,
                "playerOut": 138451,
                "time": 60,
                "incidentType": "substitution"
            },
            {
                "player": 995773,
                "card": "yellow",
                "time": 53,
                "incidentType": "card"
            },
            {
                "player": 117653,
                "card": "yellow",
                "time": 43,
                "incidentType": "card"
            },
            {
                "playerIn": 897603,
                "playerOut": 875633,
                "time": 39,
                "incidentType": "substitution"
            },
            {
                "player": 75509,
                "card": "yellow",
                "time": 36,
                "incidentType": "card"
            }
        ],
        "9578838": [
            {
                "player": 280737,
                "card": "yellow",
                "time": 90,
                "incidentType": "card"
            },
            {
                "playerIn": 797775,
                "playerOut": 836200,
                "time": 84,
                "incidentType": "substitution"
            },
            {
                "playerIn": 148190,
                "playerOut": 359802,
                "time": 84,
                "incidentType": "substitution"
            },
            {
                "playerIn": 825675,
                "playerOut": 923888,
                "time": 82,
                "incidentType": "substitution"
            },
            {
                "playerIn": 897603,
                "playerOut": 51223,
                "time": 76,
                "incidentType": "substitution"
            },
            {
                "playerIn": 1048593,
                "playerOut": 824165,
                "time": 72,
                "incidentType": "substitution"
            },
            {
                "playerIn": 943211,
                "playerOut": 921222,
                "time": 71,
                "incidentType": "substitution"
            },
            {
                "playerIn": 921764,
                "playerOut": 134877,
                "time": 66,
                "incidentType": "substitution"
            },
            {
                "playerIn": 75509,
                "playerOut": 551406,
                "time": 66,
                "incidentType": "substitution"
            },
            {
                "playerIn": 161431,
                "playerOut": 156990,
                "time": 61,
                "incidentType": "substitution"
            },
            {
                "playerIn": 280737,
                "playerOut": 1031476,
                "time": 61,
                "incidentType": "substitution"
            },
            {
                "goalscorer": 836200,
                "assist": 359802,
                "time": 17,
                "incidentType": "goal"
            }
        ],
        "9578833": [
            {
                "player": 1020921,
                "card": "yellow",
                "time": 87,
                "incidentType": "card"
            },
            {
                "playerIn": 75509,
                "playerOut": 836200,
                "time": 86,
                "incidentType": "substitution"
            },
            {
                "playerIn": 357590,
                "playerOut": 808543,
                "time": 85,
                "incidentType": "substitution"
            },
            {
                "playerIn": 970516,
                "playerOut": 551406,
                "time": 78,
                "incidentType": "substitution"
            },
            {
                "playerIn": 51223,
                "playerOut": 921764,
                "time": 78,
                "incidentType": "substitution"
            },
            {
                "goalscorer": 897603,
                "assist": 358598,
                "time": 75,
                "incidentType": "goal"
            },
            {
                "player": 857492,
                "card": "yellow",
                "time": 74,
                "incidentType": "card"
            },
            {
                "playerIn": 979368,
                "playerOut": 1020922,
                "time": 70,
                "incidentType": "substitution"
            },
            {
                "playerIn": 134877,
                "playerOut": 797775,
                "time": 64,
                "incidentType": "substitution"
            },
            {
                "playerIn": 148190,
                "playerOut": 359802,
                "time": 64,
                "incidentType": "substitution"
            },
            {
                "goalscorer": 536820,
                "assist": "N/A",
                "time": 55,
                "incidentType": "goal"
            },
            {
                "playerIn": 991390,
                "playerOut": 904669,
                "time": 46,
                "incidentType": "substitution"
            },
            {
                "playerIn": 857492,
                "playerOut": 1133727,
                "time": 46,
                "incidentType": "substitution"
            },
            {
                "player": 173675,
                "card": "yellow",
                "time": 32,
                "incidentType": "card"
            },
            {
                "goalscorer": 551406,
                "assist": 358598,
                "time": 13,
                "incidentType": "goal"
            }
        ],
        "9578829": [
            {
                "player": 70423,
                "card": "yellow",
                "time": 90,
                "incidentType": "card"
            },
            {
                "playerIn": 1048919,
                "playerOut": 799037,
                "time": 86,
                "incidentType": "substitution"
            },
            {
                "playerIn": 75509,
                "playerOut": 551406,
                "time": 77,
                "incidentType": "substitution"
            },
            {
                "playerIn": 148190,
                "playerOut": 344177,
                "time": 77,
                "incidentType": "substitution"
            },
            {
                "playerIn": 283851,
                "playerOut": 935054,
                "time": 71,
                "incidentType": "substitution"
            },
            {
                "playerIn": 134877,
                "playerOut": 797775,
                "time": 65,
                "incidentType": "substitution"
            },
            {
                "playerIn": 921764,
                "playerOut": 283855,
                "time": 65,
                "incidentType": "substitution"
            },
            {
                "playerIn": 836200,
                "playerOut": 66209,
                "time": 65,
                "incidentType": "substitution"
            },
            {
                "player": 285991,
                "card": "yellow",
                "time": 61,
                "incidentType": "card"
            },
            {
                "player": 173675,
                "card": "yellow",
                "time": 49,
                "incidentType": "card"
            },
            {
                "player": 110436,
                "card": "yellow",
                "time": 42,
                "incidentType": "card"
            },
            {
                "player": 51242,
                "card": "yellow",
                "time": 15,
                "incidentType": "card"
            }
        ],
        "9578845": [
            {
                "playerIn": 1102829,
                "playerOut": 990148,
                "time": 87,
                "incidentType": "substitution"
            },
            {
                "playerIn": 890663,
                "playerOut": 70623,
                "time": 86,
                "incidentType": "substitution"
            },
            {
                "player": 53862,
                "card": "yellow",
                "time": 80,
                "incidentType": "card"
            },
            {
                "goalscorer": 88645,
                "assist": 44679,
                "time": 77,
                "incidentType": "goal"
            },
            {
                "playerIn": 44679,
                "playerOut": 357638,
                "time": 76,
                "incidentType": "substitution"
            },
            {
                "playerIn": 53862,
                "playerOut": 1083207,
                "time": 75,
                "incidentType": "substitution"
            },
            {
                "playerIn": 1023376,
                "playerOut": 283859,
                "time": 75,
                "incidentType": "substitution"
            },
            {
                "player": 990148,
                "card": "yellow",
                "time": 70,
                "incidentType": "card"
            },
            {
                "playerIn": 309306,
                "playerOut": 855970,
                "time": 67,
                "incidentType": "substitution"
            },
            {
                "playerIn": 796206,
                "playerOut": 905063,
                "time": 67,
                "incidentType": "substitution"
            },
            {
                "player": 905063,
                "card": "yellow",
                "time": 60,
                "incidentType": "card"
            },
            {
                "player": 858501,
                "card": "yellow",
                "time": 53,
                "incidentType": "card"
            },
            {
                "playerIn": 841947,
                "playerOut": 795169,
                "time": 46,
                "incidentType": "substitution"
            },
            {
                "playerIn": 88645,
                "playerOut": 895245,
                "time": 46,
                "incidentType": "substitution"
            },
            {
                "player": 876255,
                "card": "yellow",
                "time": 38,
                "incidentType": "card"
            }
        ],
        "9578837": [
            {
                "playerIn": 53862,
                "playerOut": 990148,
                "time": 84,
                "incidentType": "substitution"
            },
            {
                "playerIn": 970524,
                "playerOut": 914217,
                "time": 84,
                "incidentType": "substitution"
            },
            {
                "playerIn": 890663,
                "playerOut": 1083207,
                "time": 72,
                "incidentType": "substitution"
            },
            {
                "playerIn": 1009516,
                "playerOut": 283859,
                "time": 72,
                "incidentType": "substitution"
            },
            {
                "player": 990141,
                "card": "yellow",
                "time": 68,
                "incidentType": "card"
            },
            {
                "player": 876255,
                "card": "yellow",
                "time": 65,
                "incidentType": "card"
            },
            {
                "playerIn": 990141,
                "playerOut": 839917,
                "time": 63,
                "incidentType": "substitution"
            },
            {
                "playerIn": 138451,
                "playerOut": 1091633,
                "time": 63,
                "incidentType": "substitution"
            },
            {
                "playerIn": 1048923,
                "playerOut": 117653,
                "time": 63,
                "incidentType": "substitution"
            },
            {
                "playerIn": 1102829,
                "playerOut": 70623,
                "time": 55,
                "incidentType": "substitution"
            },
            {
                "goalscorer": 283859,
                "assist": 914217,
                "time": 49,
                "incidentType": "goal"
            },
            {
                "playerIn": 933787,
                "playerOut": 1068519,
                "time": 46,
                "incidentType": "substitution"
            },
            {
                "playerIn": 344797,
                "playerOut": 108031,
                "time": 46,
                "incidentType": "substitution"
            },
            {
                "goalscorer": 982466,
                "assist": "N/A",
                "time": 45,
                "incidentType": "goal"
            },
            {
                "player": 117653,
                "card": "yellow",
                "time": 32,
                "incidentType": "card"
            },
            {
                "goalscorer": 982466,
                "assist": 878101,
                "time": 31,
                "incidentType": "goal"
            },
            {
                "player": 847785,
                "card": "yellow",
                "time": 24,
                "incidentType": "card"
            },
            {
                "player": 283859,
                "card": "yellow",
                "time": 21,
                "incidentType": "card"
            },
            {
                "goalscorer": 283859,
                "assist": 878101,
                "time": 20,
                "incidentType": "goal"
            },
            {
                "player": 1083207,
                "card": "yellow",
                "time": 13,
                "incidentType": "card"
            },
            {
                "player": 914217,
                "card": "yellow",
                "time": 6,
                "incidentType": "card"
            }
        ],
        "9578828": [
            {
                "playerIn": 970524,
                "playerOut": 982466,
                "time": 90,
                "incidentType": "substitution"
            },
            {
                "player": 880749,
                "card": "yellow",
                "time": 90,
                "incidentType": "card"
            },
            {
                "goalscorer": 353290,
                "assist": "N/A",
                "time": 87,
                "incidentType": "goal"
            },
            {
                "playerIn": 53862,
                "playerOut": 1083207,
                "time": 86,
                "incidentType": "substitution"
            },
            {
                "playerIn": 1022491,
                "playerOut": 283859,
                "time": 86,
                "incidentType": "substitution"
            },
            {
                "playerIn": 849318,
                "playerOut": 1020922,
                "time": 83,
                "incidentType": "substitution"
            },
            {
                "playerIn": 897602,
                "playerOut": 849316,
                "time": 82,
                "incidentType": "substitution"
            },
            {
                "goalscorer": 1083207,
                "assist": 1102829,
                "time": 80,
                "incidentType": "goal"
            },
            {
                "playerIn": 1048729,
                "playerOut": 536820,
                "time": 77,
                "incidentType": "substitution"
            },
            {
                "playerIn": 1102829,
                "playerOut": 70623,
                "time": 76,
                "incidentType": "substitution"
            },
            {
                "player": 904669,
                "card": "yellow",
                "time": 71,
                "incidentType": "card"
            },
            {
                "player": 858501,
                "card": "yellow",
                "time": 56,
                "incidentType": "card"
            },
            {
                "playerIn": 979368,
                "playerOut": 808543,
                "time": 55,
                "incidentType": "substitution"
            },
            {
                "goalscorer": 878101,
                "assist": "N/A",
                "time": 54,
                "incidentType": "goal"
            },
            {
                "playerIn": 991390,
                "playerOut": 948139,
                "time": 46,
                "incidentType": "substitution"
            },
            {
                "goalscorer": 982466,
                "assist": "N/A",
                "time": 39,
                "incidentType": "goal"
            },
            {
                "player": 849316,
                "card": "yellow",
                "time": 24,
                "incidentType": "card"
            },
            {
                "goalscorer": 1020922,
                "assist": 869707,
                "time": 14,
                "incidentType": "goal"
            }
        ],
        "9578823": [
            {
                "player": 845373,
                "card": "yellow",
                "time": 90,
                "incidentType": "card"
            },
            {
                "playerIn": 357622,
                "playerOut": 70623,
                "time": 90,
                "incidentType": "substitution"
            },
            {
                "playerIn": 53862,
                "playerOut": 982466,
                "time": 90,
                "incidentType": "substitution"
            },
            {
                "goalscorer": 70623,
                "assist": "N/A",
                "time": 89,
                "incidentType": "goal"
            },
            {
                "playerIn": 1102829,
                "playerOut": 283859,
                "time": 87,
                "incidentType": "substitution"
            },
            {
                "goalscorer": 51242,
                "assist": "N/A",
                "time": 66,
                "incidentType": "goal"
            },
            {
                "playerIn": 1048919,
                "playerOut": 935054,
                "time": 62,
                "incidentType": "substitution"
            },
            {
                "playerIn": 845373,
                "playerOut": 1048780,
                "time": 62,
                "incidentType": "substitution"
            },
            {
                "player": 935054,
                "card": "yellow",
                "time": 47,
                "incidentType": "card"
            },
            {
                "playerIn": 792156,
                "playerOut": 1120914,
                "time": 46,
                "incidentType": "substitution"
            },
            {
                "goalscorer": 990148,
                "assist": 914217,
                "time": 22,
                "incidentType": "goal"
            }
        ],
        "9578818": [
            {
                "playerIn": 53862,
                "playerOut": 1083207,
                "time": 88,
                "incidentType": "substitution"
            },
            {
                "playerIn": 1022491,
                "playerOut": 283859,
                "time": 88,
                "incidentType": "substitution"
            },
            {
                "player": 858501,
                "card": "yellow",
                "time": 84,
                "incidentType": "card"
            },
            {
                "playerIn": 970518,
                "playerOut": 75417,
                "time": 82,
                "incidentType": "substitution"
            },
            {
                "playerIn": 1090010,
                "playerOut": 965019,
                "time": 81,
                "incidentType": "substitution"
            },
            {
                "playerIn": 539260,
                "playerOut": 841985,
                "time": 73,
                "incidentType": "substitution"
            },
            {
                "playerIn": 1102829,
                "playerOut": 982466,
                "time": 70,
                "incidentType": "substitution"
            },
            {
                "player": 1083207,
                "card": "yellow",
                "time": 68,
                "incidentType": "card"
            },
            {
                "playerIn": 883475,
                "playerOut": 916181,
                "time": 61,
                "incidentType": "substitution"
            },
            {
                "playerIn": 70623,
                "playerOut": 814889,
                "time": 57,
                "incidentType": "substitution"
            },
            {
                "goalscorer": 827367,
                "assist": 94226,
                "time": 55,
                "incidentType": "goal"
            },
            {
                "goalscorer": 283859,
                "assist": 990148,
                "time": 47,
                "incidentType": "goal"
            },
            {
                "goalscorer": 991290,
                "assist": 990148,
                "time": 42,
                "incidentType": "goal"
            },
            {
                "goalscorer": 827367,
                "assist": 841985,
                "time": 29,
                "incidentType": "goal"
            }
        ],
        "9578836": [
            {
                "playerIn": 880742,
                "playerOut": 796206,
                "time": 85,
                "incidentType": "substitution"
            },
            {
                "playerIn": 882588,
                "playerOut": 885707,
                "time": 77,
                "incidentType": "substitution"
            },
            {
                "player": 895245,
                "card": "yellow",
                "time": 71,
                "incidentType": "card"
            },
            {
                "playerIn": 127844,
                "playerOut": 588162,
                "time": 70,
                "incidentType": "substitution"
            },
            {
                "playerIn": 856905,
                "playerOut": 839388,
                "time": 70,
                "incidentType": "substitution"
            },
            {
                "playerIn": 965818,
                "playerOut": 880745,
                "time": 66,
                "incidentType": "substitution"
            },
            {
                "playerIn": 826024,
                "playerOut": 795169,
                "time": 66,
                "incidentType": "substitution"
            },
            {
                "playerIn": 309306,
                "playerOut": 44679,
                "time": 65,
                "incidentType": "substitution"
            },
            {
                "player": 1103981,
                "card": "yellow",
                "time": 59,
                "incidentType": "card"
            },
            {
                "player": 286917,
                "card": "yellow",
                "time": 56,
                "incidentType": "card"
            },
            {
                "playerIn": 880751,
                "playerOut": 872262,
                "time": 46,
                "incidentType": "substitution"
            },
            {
                "playerIn": 73146,
                "playerOut": 954836,
                "time": 46,
                "incidentType": "substitution"
            },
            {
                "goalscorer": 885707,
                "assist": "N/A",
                "time": 36,
                "incidentType": "goal"
            },
            {
                "playerIn": 357638,
                "playerOut": 905063,
                "time": 33,
                "incidentType": "substitution"
            }
        ],
        "9578827": [
            {
                "playerIn": 44679,
                "playerOut": 88645,
                "time": 89,
                "incidentType": "substitution"
            },
            {
                "playerIn": 161431,
                "playerOut": 873419,
                "time": 87,
                "incidentType": "substitution"
            },
            {
                "playerIn": 922945,
                "playerOut": 943211,
                "time": 79,
                "incidentType": "substitution"
            },
            {
                "playerIn": 824165,
                "playerOut": 107025,
                "time": 79,
                "incidentType": "substitution"
            },
            {
                "playerIn": 895245,
                "playerOut": 795169,
                "time": 66,
                "incidentType": "substitution"
            },
            {
                "playerIn": 923888,
                "playerOut": 280737,
                "time": 66,
                "incidentType": "substitution"
            },
            {
                "playerIn": 921222,
                "playerOut": 887799,
                "time": 65,
                "incidentType": "substitution"
            },
            {
                "playerIn": 243713,
                "playerOut": 841947,
                "time": 65,
                "incidentType": "substitution"
            },
            {
                "playerIn": 309306,
                "playerOut": 49351,
                "time": 65,
                "incidentType": "substitution"
            },
            {
                "goalscorer": 88645,
                "assist": "N/A",
                "time": 59,
                "incidentType": "goal"
            },
            {
                "goalscorer": 107025,
                "assist": "N/A",
                "time": 43,
                "incidentType": "goal"
            },
            {
                "goalscorer": 873419,
                "assist": "N/A",
                "time": 38,
                "incidentType": "goal"
            },
            {
                "player": 44225,
                "card": "yellow",
                "time": 37,
                "incidentType": "card"
            },
            {
                "player": 887799,
                "card": "yellow",
                "time": 34,
                "incidentType": "card"
            },
            {
                "goalscorer": 841947,
                "assist": 795169,
                "time": 32,
                "incidentType": "goal"
            },
            {
                "goalscorer": 873419,
                "assist": 156990,
                "time": 23,
                "incidentType": "goal"
            },
            {
                "player": 94239,
                "card": "yellow",
                "time": 10,
                "incidentType": "card"
            },
            {
                "goalscorer": 286917,
                "assist": 880742,
                "time": 9,
                "incidentType": "goal"
            }
        ],
        "9578824": [
            {
                "playerIn": 978294,
                "playerOut": 991390,
                "time": 74,
                "incidentType": "substitution"
            },
            {
                "playerIn": 44679,
                "playerOut": 49351,
                "time": 71,
                "incidentType": "substitution"
            },
            {
                "playerIn": 309306,
                "playerOut": 841947,
                "time": 65,
                "incidentType": "substitution"
            },
            {
                "playerIn": 880749,
                "playerOut": 536820,
                "time": 56,
                "incidentType": "substitution"
            },
            {
                "playerIn": 948139,
                "playerOut": 897602,
                "time": 56,
                "incidentType": "substitution"
            },
            {
                "playerIn": 826024,
                "playerOut": 796206,
                "time": 56,
                "incidentType": "substitution"
            },
            {
                "goalscorer": 841947,
                "assist": "N/A",
                "time": 53,
                "incidentType": "goal"
            },
            {
                "playerIn": 1048729,
                "playerOut": 857492,
                "time": 52,
                "incidentType": "substitution"
            },
            {
                "goalscorer": 49351,
                "assist": 880742,
                "time": 49,
                "incidentType": "goal"
            },
            {
                "playerIn": 905063,
                "playerOut": 243713,
                "time": 46,
                "incidentType": "substitution"
            },
            {
                "playerIn": 895245,
                "playerOut": 73146,
                "time": 46,
                "incidentType": "substitution"
            },
            {
                "playerIn": 808543,
                "playerOut": 979368,
                "time": 46,
                "incidentType": "substitution"
            },
            {
                "goalscorer": 954836,
                "assist": 841947,
                "time": 35,
                "incidentType": "goal"
            },
            {
                "player": 904669,
                "card": "yellow",
                "time": 34,
                "incidentType": "card"
            },
            {
                "goalscorer": 841947,
                "assist": 954836,
                "time": 19,
                "incidentType": "goal"
            }
        ],
        "9578817": [
            {
                "player": 51188,
                "card": "yellow",
                "time": 90,
                "incidentType": "card"
            },
            {
                "playerIn": 285991,
                "playerOut": 1120914,
                "time": 86,
                "incidentType": "substitution"
            },
            {
                "goalscorer": 852471,
                "assist": 799037,
                "time": 84,
                "incidentType": "goal"
            },
            {
                "player": 852471,
                "card": "yellow",
                "time": 83,
                "incidentType": "card"
            },
            {
                "playerIn": 44679,
                "playerOut": 88645,
                "time": 74,
                "incidentType": "substitution"
            },
            {
                "playerIn": 795169,
                "playerOut": 822462,
                "time": 74,
                "incidentType": "substitution"
            },
            {
                "playerIn": 792156,
                "playerOut": 51242,
                "time": 69,
                "incidentType": "substitution"
            },
            {
                "playerIn": 845373,
                "playerOut": 1048780,
                "time": 69,
                "incidentType": "substitution"
            },
            {
                "playerIn": 243713,
                "playerOut": 942081,
                "time": 60,
                "incidentType": "substitution"
            },
            {
                "playerIn": 309306,
                "playerOut": 895245,
                "time": 60,
                "incidentType": "substitution"
            },
            {
                "playerIn": 935054,
                "playerOut": 1048919,
                "time": 60,
                "incidentType": "substitution"
            },
            {
                "goalscorer": 51242,
                "assist": "N/A",
                "time": 50,
                "incidentType": "goal"
            },
            {
                "playerIn": 841947,
                "playerOut": 357638,
                "time": 46,
                "incidentType": "substitution"
            },
            {
                "player": 110436,
                "card": "yellow",
                "time": 26,
                "incidentType": "card"
            }
        ],
        "9578843": [
            {
                "player": 1048836,
                "card": "yellow",
                "time": 86,
                "incidentType": "card"
            },
            {
                "playerIn": 888934,
                "playerOut": 1048837,
                "time": 84,
                "incidentType": "substitution"
            },
            {
                "playerIn": 1048836,
                "playerOut": 319181,
                "time": 84,
                "incidentType": "substitution"
            },
            {
                "playerIn": 359028,
                "playerOut": 822505,
                "time": 76,
                "incidentType": "substitution"
            },
            {
                "goalscorer": 1048593,
                "assist": 923888,
                "time": 76,
                "incidentType": "goal"
            },
            {
                "playerIn": 995774,
                "playerOut": 51157,
                "time": 76,
                "incidentType": "substitution"
            },
            {
                "playerIn": 1048593,
                "playerOut": 316443,
                "time": 76,
                "incidentType": "substitution"
            },
            {
                "player": 1048837,
                "card": "yellow",
                "time": 76,
                "incidentType": "card"
            },
            {
                "playerIn": 69373,
                "playerOut": 824165,
                "time": 64,
                "incidentType": "substitution"
            },
            {
                "goalscorer": 107025,
                "assist": "N/A",
                "time": 64,
                "incidentType": "goal"
            },
            {
                "player": 966477,
                "card": "yellow",
                "time": 62,
                "incidentType": "card"
            },
            {
                "playerIn": 107025,
                "playerOut": 964991,
                "time": 52,
                "incidentType": "substitution"
            },
            {
                "playerIn": 70298,
                "playerOut": 797920,
                "time": 52,
                "incidentType": "substitution"
            },
            {
                "goalscorer": 822505,
                "assist": 897600,
                "time": 47,
                "incidentType": "goal"
            },
            {
                "playerIn": 923888,
                "playerOut": 887798,
                "time": 46,
                "incidentType": "substitution"
            },
            {
                "playerIn": 94239,
                "playerOut": 921222,
                "time": 46,
                "incidentType": "substitution"
            },
            {
                "player": 921222,
                "card": "yellow",
                "time": 31,
                "incidentType": "card"
            },
            {
                "player": 283849,
                "card": "yellow",
                "time": 14,
                "incidentType": "card"
            },
            {
                "player": 51157,
                "card": "yellow",
                "time": 5,
                "incidentType": "card"
            }
        ],
        "9578825": [
            {
                "player": 1130127,
                "card": "yellow",
                "time": 90,
                "incidentType": "card"
            },
            {
                "playerIn": 1031476,
                "playerOut": 107025,
                "time": 90,
                "incidentType": "substitution"
            },
            {
                "playerIn": 1130127,
                "playerOut": 869746,
                "time": 85,
                "incidentType": "substitution"
            },
            {
                "playerIn": 933787,
                "playerOut": 108031,
                "time": 84,
                "incidentType": "substitution"
            },
            {
                "goalscorer": 107025,
                "assist": 94239,
                "time": 82,
                "incidentType": "goal"
            },
            {
                "player": 824165,
                "card": "yellow",
                "time": 81,
                "incidentType": "card"
            },
            {
                "goalscorer": 107025,
                "assist": 50577,
                "time": 78,
                "incidentType": "goal"
            },
            {
                "playerIn": 839917,
                "playerOut": 990141,
                "time": 77,
                "incidentType": "substitution"
            },
            {
                "playerIn": 995773,
                "playerOut": 845070,
                "time": 67,
                "incidentType": "substitution"
            },
            {
                "playerIn": 887799,
                "playerOut": 770399,
                "time": 66,
                "incidentType": "substitution"
            },
            {
                "playerIn": 824165,
                "playerOut": 280737,
                "time": 46,
                "incidentType": "substitution"
            },
            {
                "player": 869746,
                "card": "yellow",
                "time": 44,
                "incidentType": "card"
            },
            {
                "player": 233652,
                "card": "yellow",
                "time": 25,
                "incidentType": "card"
            },
            {
                "player": 117653,
                "card": "yellow",
                "time": 17,
                "incidentType": "card"
            }
        ],
        "9578816": [
            {
                "playerIn": 880745,
                "playerOut": 826023,
                "time": 83,
                "incidentType": "substitution"
            },
            {
                "playerIn": 283841,
                "playerOut": 839388,
                "time": 82,
                "incidentType": "substitution"
            },
            {
                "playerIn": 887798,
                "playerOut": 283853,
                "time": 80,
                "incidentType": "substitution"
            },
            {
                "playerIn": 824165,
                "playerOut": 107025,
                "time": 75,
                "incidentType": "substitution"
            },
            {
                "playerIn": 916183,
                "playerOut": 880751,
                "time": 66,
                "incidentType": "substitution"
            },
            {
                "playerIn": 127844,
                "playerOut": 882588,
                "time": 65,
                "incidentType": "substitution"
            },
            {
                "goalscorer": 887799,
                "assist": 283853,
                "time": 54,
                "incidentType": "goal"
            },
            {
                "playerIn": 1048593,
                "playerOut": 770399,
                "time": 53,
                "incidentType": "substitution"
            },
            {
                "goalscorer": 283853,
                "assist": "N/A",
                "time": 20,
                "incidentType": "goal"
            },
            {
                "player": 951182,
                "card": "yellow",
                "time": 19,
                "incidentType": "card"
            },
            {
                "player": 839388,
                "card": "yellow",
                "time": 12,
                "incidentType": "card"
            }
        ],
        "9578841": [
            {
                "playerIn": 880745,
                "playerOut": 826023,
                "time": 90,
                "incidentType": "substitution"
            },
            {
                "playerIn": 916183,
                "playerOut": 359044,
                "time": 89,
                "incidentType": "substitution"
            },
            {
                "playerIn": 882731,
                "playerOut": 852471,
                "time": 86,
                "incidentType": "substitution"
            },
            {
                "player": 814879,
                "card": "yellow",
                "time": 83,
                "incidentType": "card"
            },
            {
                "player": 754140,
                "card": "yellow",
                "time": 82,
                "incidentType": "card"
            },
            {
                "player": 946040,
                "card": "yellow",
                "time": 80,
                "incidentType": "card"
            },
            {
                "playerIn": 70423,
                "playerOut": 110436,
                "time": 78,
                "incidentType": "substitution"
            },
            {
                "playerIn": 1048780,
                "playerOut": 792156,
                "time": 73,
                "incidentType": "substitution"
            },
            {
                "playerIn": 1048919,
                "playerOut": 799037,
                "time": 72,
                "incidentType": "substitution"
            },
            {
                "playerIn": 845373,
                "playerOut": 283851,
                "time": 72,
                "incidentType": "substitution"
            },
            {
                "goalscorer": 127844,
                "assist": 826023,
                "time": 66,
                "incidentType": "goal"
            },
            {
                "playerIn": 754140,
                "playerOut": 880751,
                "time": 66,
                "incidentType": "substitution"
            },
            {
                "playerIn": 127844,
                "playerOut": 882588,
                "time": 65,
                "incidentType": "substitution"
            },
            {
                "playerIn": 856905,
                "playerOut": 839388,
                "time": 65,
                "incidentType": "substitution"
            },
            {
                "player": 110436,
                "card": "yellow",
                "time": 64,
                "incidentType": "card"
            },
            {
                "player": 885707,
                "card": "yellow",
                "time": 12,
                "incidentType": "card"
            }
        ],
        "9578826": [
            {
                "player": 233652,
                "card": "yellow",
                "time": 90,
                "incidentType": "card"
            },
            {
                "goalscorer": 886227,
                "assist": 847785,
                "time": 90,
                "incidentType": "goal"
            },
            {
                "playerIn": 965818,
                "playerOut": 880751,
                "time": 87,
                "incidentType": "substitution"
            },
            {
                "playerIn": 283841,
                "playerOut": 839388,
                "time": 81,
                "incidentType": "substitution"
            },
            {
                "playerIn": 344797,
                "playerOut": 117653,
                "time": 81,
                "incidentType": "substitution"
            },
            {
                "playerIn": 933787,
                "playerOut": 1034543,
                "time": 81,
                "incidentType": "substitution"
            },
            {
                "player": 359044,
                "card": "yellow",
                "time": 77,
                "incidentType": "card"
            },
            {
                "playerIn": 995773,
                "playerOut": 845070,
                "time": 72,
                "incidentType": "substitution"
            },
            {
                "player": 92980,
                "card": "yellow",
                "time": 72,
                "incidentType": "card"
            },
            {
                "player": 869746,
                "card": "yellow",
                "time": 71,
                "incidentType": "card"
            },
            {
                "goalscorer": 839388,
                "assist": 127844,
                "time": 68,
                "incidentType": "goal"
            },
            {
                "playerIn": 127844,
                "playerOut": 916183,
                "time": 64,
                "incidentType": "substitution"
            },
            {
                "playerIn": 196094,
                "playerOut": 588162,
                "time": 46,
                "incidentType": "substitution"
            },
            {
                "player": 588162,
                "card": "yellow",
                "time": 42,
                "incidentType": "card"
            },
            {
                "goalscorer": 359044,
                "assist": "N/A",
                "time": 19,
                "incidentType": "goal"
            },
            {
                "player": 946040,
                "card": "yellow",
                "time": 10,
                "incidentType": "card"
            }
        ],
        "9578821": [
            {
                "player": 916183,
                "card": "yellow",
                "time": 88,
                "incidentType": "card"
            },
            {
                "playerIn": 880745,
                "playerOut": 92980,
                "time": 88,
                "incidentType": "substitution"
            },
            {
                "playerIn": 196094,
                "playerOut": 359044,
                "time": 87,
                "incidentType": "substitution"
            },
            {
                "goalscorer": 848540,
                "assist": 822505,
                "time": 87,
                "incidentType": "goal"
            },
            {
                "player": 136705,
                "card": "yellow",
                "time": 85,
                "incidentType": "card"
            },
            {
                "playerIn": 359028,
                "playerOut": 897600,
                "time": 82,
                "incidentType": "substitution"
            },
            {
                "playerIn": 283841,
                "playerOut": 839388,
                "time": 80,
                "incidentType": "substitution"
            },
            {
                "player": 916186,
                "card": "yellow",
                "time": 72,
                "incidentType": "card"
            },
            {
                "playerIn": 916186,
                "playerOut": 855970,
                "time": 70,
                "incidentType": "substitution"
            },
            {
                "playerIn": 797920,
                "playerOut": 879722,
                "time": 70,
                "incidentType": "substitution"
            },
            {
                "goalscorer": 359044,
                "assist": 916183,
                "time": 69,
                "incidentType": "goal"
            },
            {
                "goalscorer": 839388,
                "assist": 359624,
                "time": 66,
                "incidentType": "goal"
            },
            {
                "playerIn": 916183,
                "playerOut": 882588,
                "time": 61,
                "incidentType": "substitution"
            },
            {
                "playerIn": 127844,
                "playerOut": 880751,
                "time": 61,
                "incidentType": "substitution"
            },
            {
                "playerIn": 319149,
                "playerOut": 70298,
                "time": 55,
                "incidentType": "substitution"
            },
            {
                "player": 588162,
                "card": "yellow",
                "time": 50,
                "incidentType": "card"
            },
            {
                "player": 319181,
                "card": "yellow",
                "time": 43,
                "incidentType": "card"
            },
            {
                "goalscorer": 826023,
                "assist": 359044,
                "time": 26,
                "incidentType": "goal"
            },
            {
                "player": 855970,
                "card": "yellow",
                "time": -5,
                "incidentType": "card"
            }
        ],
        "9578820": [
            {
                "playerIn": 1103103,
                "playerOut": 991390,
                "time": 90,
                "incidentType": "substitution"
            },
            {
                "goalscorer": 1020922,
                "assist": 869707,
                "time": 90,
                "incidentType": "goal"
            },
            {
                "playerIn": 1130127,
                "playerOut": 886854,
                "time": 85,
                "incidentType": "substitution"
            },
            {
                "player": 849316,
                "card": "yellow",
                "time": 77,
                "incidentType": "card"
            },
            {
                "playerIn": 1034543,
                "playerOut": 117653,
                "time": 74,
                "incidentType": "substitution"
            },
            {
                "playerIn": 995773,
                "playerOut": 845070,
                "time": 74,
                "incidentType": "substitution"
            },
            {
                "playerIn": 933787,
                "playerOut": 108031,
                "time": 66,
                "incidentType": "substitution"
            },
            {
                "playerIn": 1020922,
                "playerOut": 83487,
                "time": 54,
                "incidentType": "substitution"
            },
            {
                "playerIn": 857492,
                "playerOut": 808543,
                "time": 54,
                "incidentType": "substitution"
            },
            {
                "player": 108031,
                "card": "yellow",
                "time": 49,
                "incidentType": "card"
            },
            {
                "playerIn": 897602,
                "playerOut": 904669,
                "time": 46,
                "incidentType": "substitution"
            },
            {
                "goalscorer": 233652,
                "assist": 108031,
                "time": 45,
                "incidentType": "goal"
            },
            {
                "player": 83487,
                "card": "yellow",
                "time": 45,
                "incidentType": "card"
            },
            {
                "player": 991390,
                "card": "yellow",
                "time": 34,
                "incidentType": "card"
            },
            {
                "playerIn": 979368,
                "playerOut": 951290,
                "time": 29,
                "incidentType": "substitution"
            },
            {
                "player": 951290,
                "card": "yellow",
                "time": 29,
                "incidentType": "card"
            },
            {
                "goalscorer": 886227,
                "assist": "N/A",
                "time": 17,
                "incidentType": "goal"
            },
            {
                "goalscorer": 886227,
                "assist": 869746,
                "time": 10,
                "incidentType": "goal"
            }
        ],
        "9578850": [
            {
                "playerIn": 366848,
                "playerOut": 314336,
                "time": 90,
                "incidentType": "substitution"
            },
            {
                "playerIn": 285991,
                "playerOut": 852471,
                "time": 89,
                "incidentType": "substitution"
            },
            {
                "playerIn": 1048919,
                "playerOut": 935054,
                "time": 89,
                "incidentType": "substitution"
            },
            {
                "goalscorer": 314336,
                "assist": "N/A",
                "time": 85,
                "incidentType": "goal"
            },
            {
                "player": 284843,
                "card": "yellow",
                "time": 81,
                "incidentType": "card"
            },
            {
                "player": 808503,
                "card": "yellow",
                "time": 79,
                "incidentType": "card"
            },
            {
                "playerIn": 886851,
                "playerOut": 857492,
                "time": 77,
                "incidentType": "substitution"
            },
            {
                "player": 799037,
                "card": "yellowRed",
                "time": 76,
                "incidentType": "card"
            },
            {
                "playerIn": 1048780,
                "playerOut": 792156,
                "time": 73,
                "incidentType": "substitution"
            },
            {
                "playerIn": 979368,
                "playerOut": 798865,
                "time": 72,
                "incidentType": "substitution"
            },
            {
                "player": 51242,
                "card": "yellow",
                "time": 63,
                "incidentType": "card"
            },
            {
                "playerIn": 855908,
                "playerOut": 845373,
                "time": 61,
                "incidentType": "substitution"
            },
            {
                "playerIn": 283851,
                "playerOut": 1120914,
                "time": 61,
                "incidentType": "substitution"
            },
            {
                "player": 792156,
                "card": "yellow",
                "time": 61,
                "incidentType": "card"
            },
            {
                "playerIn": 808503,
                "playerOut": 808543,
                "time": 46,
                "incidentType": "substitution"
            },
            {
                "player": 799037,
                "card": "yellow",
                "time": 43,
                "incidentType": "card"
            }
        ],
        "9578832": [
            {
                "goalscorer": 792156,
                "assist": 51242,
                "time": 87,
                "incidentType": "goal"
            },
            {
                "playerIn": 935054,
                "playerOut": 285991,
                "time": 83,
                "incidentType": "substitution"
            },
            {
                "playerIn": 1127494,
                "playerOut": 319149,
                "time": 80,
                "incidentType": "substitution"
            },
            {
                "player": 319149,
                "card": "yellow",
                "time": 77,
                "incidentType": "card"
            },
            {
                "playerIn": 855908,
                "playerOut": 845373,
                "time": 76,
                "incidentType": "substitution"
            },
            {
                "playerIn": 792156,
                "playerOut": 902370,
                "time": 76,
                "incidentType": "substitution"
            },
            {
                "player": 51242,
                "card": "yellow",
                "time": 72,
                "incidentType": "card"
            },
            {
                "playerIn": 797920,
                "playerOut": 822505,
                "time": 69,
                "incidentType": "substitution"
            },
            {
                "playerIn": 879392,
                "playerOut": 879722,
                "time": 64,
                "incidentType": "substitution"
            },
            {
                "playerIn": 283851,
                "playerOut": 1120914,
                "time": 46,
                "incidentType": "substitution"
            },
            {
                "playerIn": 814879,
                "playerOut": 110436,
                "time": 46,
                "incidentType": "substitution"
            },
            {
                "player": 319181,
                "card": "yellow",
                "time": 45,
                "incidentType": "card"
            },
            {
                "goalscorer": 319149,
                "assist": 966477,
                "time": 33,
                "incidentType": "goal"
            },
            {
                "player": 799037,
                "card": "yellow",
                "time": 27,
                "incidentType": "card"
            }
        ],
        "9578839": [
            {
                "goalscorer": 879722,
                "assist": 319149,
                "time": 90,
                "incidentType": "goal"
            },
            {
                "goalscorer": 70298,
                "assist": 897600,
                "time": 86,
                "incidentType": "goal"
            },
            {
                "player": 1133727,
                "card": "yellow",
                "time": 85,
                "incidentType": "card"
            },
            {
                "playerIn": 1133727,
                "playerOut": 849316,
                "time": 84,
                "incidentType": "substitution"
            },
            {
                "playerIn": 995774,
                "playerOut": 848540,
                "time": 80,
                "incidentType": "substitution"
            },
            {
                "playerIn": 357590,
                "playerOut": 314336,
                "time": 77,
                "incidentType": "substitution"
            },
            {
                "playerIn": 359028,
                "playerOut": 822505,
                "time": 74,
                "incidentType": "substitution"
            },
            {
                "playerIn": 1127494,
                "playerOut": 1048837,
                "time": 73,
                "incidentType": "substitution"
            },
            {
                "player": 70298,
                "card": "yellow",
                "time": 73,
                "incidentType": "card"
            },
            {
                "player": 849316,
                "card": "yellow",
                "time": 66,
                "incidentType": "card"
            },
            {
                "playerIn": 808503,
                "playerOut": 808543,
                "time": 66,
                "incidentType": "substitution"
            },
            {
                "playerIn": 991390,
                "playerOut": 857492,
                "time": 66,
                "incidentType": "substitution"
            },
            {
                "playerIn": 849318,
                "playerOut": 1020922,
                "time": 65,
                "incidentType": "substitution"
            },
            {
                "playerIn": 319181,
                "playerOut": 51157,
                "time": 62,
                "incidentType": "substitution"
            },
            {
                "goalscorer": 319149,
                "assist": 1048837,
                "time": 61,
                "incidentType": "goal"
            },
            {
                "goalscorer": 879722,
                "assist": 319149,
                "time": 58,
                "incidentType": "goal"
            },
            {
                "goalscorer": 70298,
                "assist": 319149,
                "time": 52,
                "incidentType": "goal"
            },
            {
                "playerIn": 70298,
                "playerOut": 797920,
                "time": 46,
                "incidentType": "substitution"
            },
            {
                "goalscorer": 798865,
                "assist": 857492,
                "time": 45,
                "incidentType": "goal"
            },
            {
                "player": 1020922,
                "card": "yellow",
                "time": 44,
                "incidentType": "card"
            },
            {
                "player": 797920,
                "card": "yellow",
                "time": 43,
                "incidentType": "card"
            },
            {
                "player": 353290,
                "card": "yellow",
                "time": 40,
                "incidentType": "card"
            },
            {
                "goalscorer": 808543,
                "assist": 857492,
                "time": 34,
                "incidentType": "goal"
            },
            {
                "goalscorer": 822505,
                "assist": 1048837,
                "time": 1,
                "incidentType": "goal"
            }
        ]
    }
}